<?xml version="1.0" encoding="UTF-8"?>
<objects serializationModel="Studio.02.02.00">
	<object class="AudioFile" id="{dd7d8d64-290a-4b4a-ac50-35ca57f83156}">
		<property name="assetPath">
			<value>Ambience/Ambience/Effects/Rocks/StoneSetDown.mp3</value>
		</property>
		<property name="frequencyInKHz">
			<value>48</value>
		</property>
		<property name="channelCount">
			<value>2</value>
		</property>
		<property name="length">
			<value>0.40799999999999997</value>
		</property>
		<relationship name="masterAssetFolder">
			<destination>{dc8e9c20-4e52-45d4-b499-31bd1c0d2edb}</destination>
		</relationship>
	</object>
</objects>
